pylfl/__init__.py
pylfl/functions.py
pylfl/make_trees.py
pylfl/maketempfiles.py
pylfl/bin/linux/GMIN
pylfl/bin/linux/OPTIM
pylfl/bin/linux/PATHSAMPLE
pylfl/bin/linux/disconnectionDPS
pylfl/bin/mac/GMIN
pylfl/bin/mac/OPTIM
pylfl/bin/mac/PATHSAMPLE
pylfl/bin/mac/disconnectionDPS
pylfl/bin/win/GMIN.exe
pylfl/bin/win/OPTIM.exe
pylfl/bin/win/PATHSAMPLE.exe
pylfl/bin/win/cyggcc_s-seh-1.dll
pylfl/bin/win/cyggfortran-5.dll
pylfl/bin/win/cygquadmath-0.dll
pylfl/bin/win/cygstdc++-6.dll
pylfl/bin/win/cygwin1.dll
pylfl/bin/win/disconnectionDPS.exe
pylfl-0.3.4.dist-info/LICENSE
pylfl-0.3.4.dist-info/METADATA
pylfl-0.3.4.dist-info/WHEEL
pylfl-0.3.4.dist-info/top_level.txt
pylfl-0.3.4.dist-info/RECORD
