Metadata-Version: 2.1
Name: pylfl
Version: 0.3.4
Summary: A package to survey LFLs in ML models
Home-page: https://github.com/orinxam/pylfl
Author: Max Niroomand
Author-email: mpn26@cam.ac.uk
License: UNKNOWN
Project-URL: Bug Tracker, https://github.com/orinxam/pylfl/issues
Platform: UNKNOWN
Classifier: Programming Language :: Python :: 3
Classifier: License :: OSI Approved :: MIT License
Classifier: Operating System :: OS Independent
Requires-Python: >=3.6
License-File: LICENSE
